llama_token_counter/__init__.py
llama_token_counter/counter.py
llama_token_counter/custom_tokenizer.py
llama_token_counter/download_tokenizer_files.py
llama_token_counter/tokenizer/tokenizer.json
llama_token_counter/tokenizer/tokenizer.model
llama_token_counter/tokenizer/tokenizer_config.json
llama3.2_token_counter-0.5.0.dist-info/LICENSE
llama3.2_token_counter-0.5.0.dist-info/METADATA
llama3.2_token_counter-0.5.0.dist-info/WHEEL
llama3.2_token_counter-0.5.0.dist-info/top_level.txt
llama3.2_token_counter-0.5.0.dist-info/RECORD
