Metadata-Version: 2.1
Name: llama3.2-token-counter
Version: 0.5.0
Summary: A simple token counter for Llama 3.2 models.
Home-page: https://github.com/anthoeknee/llama3.2-token-counter
Author: anthoeknee
Author-email: pacyheb@protonmail.com
Project-URL: Bug Tracker, https://github.com/anthoeknee/llama3.2-token-counter/issues
Classifier: Development Status :: 3 - Alpha
Classifier: Intended Audience :: Developers
Classifier: License :: OSI Approved :: MIT License
Classifier: Operating System :: OS Independent
Classifier: Programming Language :: Python :: 3
Classifier: Programming Language :: Python :: 3.11
Requires-Python: >=3.11
License-File: LICENSE
Requires-Dist: regex==2023.6.3
Requires-Dist: pytest==7.3.1
